setup.cfg
setup.py
my_first_package/__init__.py
my_first_package/my_module.py
my_first_package.egg-info/PKG-INFO
my_first_package.egg-info/SOURCES.txt
my_first_package.egg-info/dependency_links.txt
my_first_package.egg-info/entry_points.txt
my_first_package.egg-info/not-zip-safe
my_first_package.egg-info/top_level.txt