Metadata-Version: 1.0
Name: my-first-package
Version: 1.0.dev0
Summary: First package
Home-page: UNKNOWN
Author: valentyn malenchak
Author-email: UNKNOWN
License: UNKNOWN
Keywords: max num
Platform: UNKNOWN
